ticos_client/__init__.py
ticos_client/config.py
ticos_client/enums.py
ticos_client/http_util.py
ticos_client/models.py
ticos_client/py.typed
ticos_client/server.py
ticos_client/storage.py
ticos_client/ticos_client.py
ticos_client/ticos_client_interface.py
ticos_client/utils.py
ticos_client/websocket_client.py
ticos_client-0.7.2.dist-info/METADATA
ticos_client-0.7.2.dist-info/WHEEL
ticos_client-0.7.2.dist-info/top_level.txt
ticos_client-0.7.2.dist-info/RECORD
