Metadata-Version: 2.4
Name: ticos-client
Version: 0.7.2
Summary: A client SDK for the Ticos Agent system with HTTP and WebSocket support
Home-page: https://github.com/tiwater/ticos-client
Author: Ticos Team
Author-email: admin@tiwater.com
Project-URL: Bug Reports, https://github.com/tiwater/ticos-client/issues
Project-URL: Source, https://github.com/tiwater/ticos-client
Classifier: Development Status :: 4 - Beta
Classifier: Intended Audience :: Developers
Classifier: License :: OSI Approved :: Apache Software License
Classifier: Operating System :: OS Independent
Classifier: Programming Language :: Python :: 3
Classifier: Programming Language :: Python :: 3.8
Classifier: Programming Language :: Python :: 3.9
Classifier: Programming Language :: Python :: 3.10
Classifier: Topic :: Software Development :: Libraries :: Python Modules
Classifier: Typing :: Typed
Requires-Python: >=3.8
Requires-Dist: fastapi<1.0.0,>=0.68.0
Requires-Dist: uvicorn<1.0.0,>=0.15.0
Requires-Dist: pydantic<2.0.0,>=1.8.0
Requires-Dist: python-multipart<1.0.0,>=0.0.5
Requires-Dist: python-jose[cryptography]<4.0.0,>=3.3.0
Requires-Dist: passlib[bcrypt]<2.0.0,>=1.7.4
Requires-Dist: python-dotenv<1.0.0,>=0.19.0
Requires-Dist: SQLAlchemy<2.0.0,>=1.4.0
Requires-Dist: alembic<2.0.0,>=1.7.0
Requires-Dist: python-dateutil<3.0.0,>=2.8.2
Requires-Dist: toml<1.0.0,>=0.10.0
Requires-Dist: uvicorn[standard]<1.0.0,>=0.15.0
Requires-Dist: requests<3.0.0,>=2.26.0
Requires-Dist: websocket-client<2.0.0,>=1.5.0
Requires-Dist: httpx<1.0.0,>=0.23.0
Provides-Extra: dev
Requires-Dist: pytest>=6.0; extra == "dev"
Requires-Dist: pytest-cov>=2.0; extra == "dev"
Requires-Dist: mypy>=0.910; extra == "dev"
Requires-Dist: black>=21.7b0; extra == "dev"
Requires-Dist: isort>=5.9.0; extra == "dev"
Requires-Dist: flake8>=3.9.0; extra == "dev"
Dynamic: author
Dynamic: author-email
Dynamic: classifier
Dynamic: description
Dynamic: description-content-type
Dynamic: home-page
Dynamic: project-url
Dynamic: provides-extra
Dynamic: requires-dist
Dynamic: requires-python
Dynamic: summary
